[
{
    "model": "financings.paymentplan",
    "pk": 13,
    "fields": {
        "mes": 1,
        "start_date": "2024-10-01T06:00:00Z",
        "due_date": "2024-11-01T06:00:00Z",
        "outstanding_balance": "2000.00",
        "mora": "20.00",
        "interest": "200.00",
        "principal": "0.00",
        "principal_pagado": "0.00",
        "installment": "804.23",
        "status": false,
        "credit_id": 2,
        "saldo_pendiente": "2000.00",
        "interes_pagado": "0.00",
        "mora_pagado": "0.00",
        "fecha_limite": "2024-11-17T06:00:00Z",
        "cambios": false,
        "numero_referencia": "NAN",
        "cuota_vencida": true,
        "interes_generado": "200.00",
        "capital_generado": "604.23",
        "interes_acumulado_generado": "0.00",
        "mora_acumulado_generado": "0.00",
        "mora_generado": "0.00",
        "paso_por_task": false
    }
},
{
    "model": "financings.paymentplan",
    "pk": 14,
    "fields": {
        "mes": 2,
        "start_date": "2024-11-01T06:00:00Z",
        "due_date": "2024-12-01T06:00:00Z",
        "outstanding_balance": "2000.00",
        "mora": "40.00",
        "interest": "400.00",
        "principal": "0.00",
        "principal_pagado": "0.00",
        "installment": "804.23",
        "status": false,
        "credit_id": 2,
        "saldo_pendiente": "2000.00",
        "interes_pagado": "0.00",
        "mora_pagado": "0.00",
        "fecha_limite": "2024-12-17T06:00:00Z",
        "cambios": false,
        "numero_referencia": "NAN",
        "cuota_vencida": true,
        "interes_generado": "200.00",
        "capital_generado": "604.23",
        "interes_acumulado_generado": "200.00",
        "mora_acumulado_generado": "20.00",
        "mora_generado": "0.00",
        "paso_por_task": false
    }
},
{
    "model": "financings.paymentplan",
    "pk": 15,
    "fields": {
        "mes": 3,
        "start_date": "2024-12-01T06:00:00Z",
        "due_date": "2025-01-01T06:00:00Z",
        "outstanding_balance": "2000.00",
        "mora": "40.00",
        "interest": "600.00",
        "principal": "0.00",
        "principal_pagado": "0.00",
        "installment": "804.23",
        "status": false,
        "credit_id": 2,
        "saldo_pendiente": "2000.00",
        "interes_pagado": "0.00",
        "mora_pagado": "0.00",
        "fecha_limite": "2025-01-17T06:00:00Z",
        "cambios": false,
        "numero_referencia": "NAN",
        "cuota_vencida": false,
        "interes_generado": "200.00",
        "capital_generado": "604.23",
        "interes_acumulado_generado": "400.00",
        "mora_acumulado_generado": "40.00",
        "mora_generado": "0.00",
        "paso_por_task": false
    }
},
{
    "model": "financings.paymentplan",
    "pk": 16,
    "fields": {
        "mes": 1,
        "start_date": "2024-10-02T06:00:00Z",
        "due_date": "2024-11-02T06:00:00Z",
        "outstanding_balance": "5000.00",
        "mora": "50.00",
        "interest": "500.00",
        "principal": "0.00",
        "principal_pagado": "0.00",
        "installment": "2010.57",
        "status": false,
        "credit_id": 3,
        "saldo_pendiente": "5000.00",
        "interes_pagado": "0.00",
        "mora_pagado": "0.00",
        "fecha_limite": "2024-11-18T06:00:00Z",
        "cambios": false,
        "numero_referencia": "NAN",
        "cuota_vencida": true,
        "interes_generado": "500.00",
        "capital_generado": "1510.57",
        "interes_acumulado_generado": "0.00",
        "mora_acumulado_generado": "0.00",
        "mora_generado": "0.00",
        "paso_por_task": false
    }
},
{
    "model": "financings.paymentplan",
    "pk": 17,
    "fields": {
        "mes": 2,
        "start_date": "2024-11-02T06:00:00Z",
        "due_date": "2024-12-02T06:00:00Z",
        "outstanding_balance": "5000.00",
        "mora": "100.00",
        "interest": "1000.00",
        "principal": "0.00",
        "principal_pagado": "0.00",
        "installment": "2010.57",
        "status": false,
        "credit_id": 3,
        "saldo_pendiente": "5000.00",
        "interes_pagado": "0.00",
        "mora_pagado": "0.00",
        "fecha_limite": "2024-12-18T06:00:00Z",
        "cambios": false,
        "numero_referencia": "NAN",
        "cuota_vencida": true,
        "interes_generado": "500.00",
        "capital_generado": "1510.57",
        "interes_acumulado_generado": "500.00",
        "mora_acumulado_generado": "50.00",
        "mora_generado": "0.00",
        "paso_por_task": false
    }
},
{
    "model": "financings.paymentplan",
    "pk": 18,
    "fields": {
        "mes": 3,
        "start_date": "2024-12-02T06:00:00Z",
        "due_date": "2025-01-02T06:00:00Z",
        "outstanding_balance": "5000.00",
        "mora": "100.00",
        "interest": "1500.00",
        "principal": "0.00",
        "principal_pagado": "0.00",
        "installment": "2010.57",
        "status": false,
        "credit_id": 3,
        "saldo_pendiente": "5000.00",
        "interes_pagado": "0.00",
        "mora_pagado": "0.00",
        "fecha_limite": "2025-01-18T06:00:00Z",
        "cambios": false,
        "numero_referencia": "NAN",
        "cuota_vencida": false,
        "interes_generado": "500.00",
        "capital_generado": "1510.57",
        "interes_acumulado_generado": "1000.00",
        "mora_acumulado_generado": "100.00",
        "mora_generado": "0.00",
        "paso_por_task": false
    }
},
{
    "model": "financings.paymentplan",
    "pk": 19,
    "fields": {
        "mes": 1,
        "start_date": "2024-10-02T06:00:00Z",
        "due_date": "2024-11-02T06:00:00Z",
        "outstanding_balance": "3000.00",
        "mora": "30.00",
        "interest": "300.00",
        "principal": "0.00",
        "principal_pagado": "0.00",
        "installment": "1206.34",
        "status": false,
        "credit_id": 4,
        "saldo_pendiente": "3000.00",
        "interes_pagado": "0.00",
        "mora_pagado": "0.00",
        "fecha_limite": "2024-11-18T06:00:00Z",
        "cambios": false,
        "numero_referencia": "NAN",
        "cuota_vencida": true,
        "interes_generado": "300.00",
        "capital_generado": "906.34",
        "interes_acumulado_generado": "0.00",
        "mora_acumulado_generado": "0.00",
        "mora_generado": "0.00",
        "paso_por_task": false
    }
},
{
    "model": "financings.paymentplan",
    "pk": 20,
    "fields": {
        "mes": 2,
        "start_date": "2024-11-02T06:00:00Z",
        "due_date": "2024-12-02T06:00:00Z",
        "outstanding_balance": "3000.00",
        "mora": "60.00",
        "interest": "600.00",
        "principal": "0.00",
        "principal_pagado": "0.00",
        "installment": "1206.34",
        "status": false,
        "credit_id": 4,
        "saldo_pendiente": "3000.00",
        "interes_pagado": "0.00",
        "mora_pagado": "0.00",
        "fecha_limite": "2024-12-18T06:00:00Z",
        "cambios": false,
        "numero_referencia": "NAN",
        "cuota_vencida": true,
        "interes_generado": "300.00",
        "capital_generado": "906.34",
        "interes_acumulado_generado": "300.00",
        "mora_acumulado_generado": "30.00",
        "mora_generado": "0.00",
        "paso_por_task": false
    }
},
{
    "model": "financings.paymentplan",
    "pk": 21,
    "fields": {
        "mes": 3,
        "start_date": "2024-12-02T06:00:00Z",
        "due_date": "2025-01-02T06:00:00Z",
        "outstanding_balance": "3000.00",
        "mora": "60.00",
        "interest": "900.00",
        "principal": "0.00",
        "principal_pagado": "0.00",
        "installment": "1206.34",
        "status": false,
        "credit_id": 4,
        "saldo_pendiente": "3000.00",
        "interes_pagado": "0.00",
        "mora_pagado": "0.00",
        "fecha_limite": "2025-01-18T06:00:00Z",
        "cambios": false,
        "numero_referencia": "NAN",
        "cuota_vencida": false,
        "interes_generado": "300.00",
        "capital_generado": "906.34",
        "interes_acumulado_generado": "600.00",
        "mora_acumulado_generado": "60.00",
        "mora_generado": "0.00",
        "paso_por_task": false
    }
},
{
    "model": "financings.paymentplan",
    "pk": 22,
    "fields": {
        "mes": 1,
        "start_date": "2024-10-02T06:00:00Z",
        "due_date": "2024-11-02T06:00:00Z",
        "outstanding_balance": "1096.00",
        "mora": "10.96",
        "interest": "109.60",
        "principal": "0.00",
        "principal_pagado": "0.00",
        "installment": "1205.60",
        "status": false,
        "credit_id": 5,
        "saldo_pendiente": "1096.00",
        "interes_pagado": "0.00",
        "mora_pagado": "0.00",
        "fecha_limite": "2024-11-18T06:00:00Z",
        "cambios": false,
        "numero_referencia": "NAN",
        "cuota_vencida": true,
        "interes_generado": "109.60",
        "capital_generado": "1096.00",
        "interes_acumulado_generado": "0.00",
        "mora_acumulado_generado": "0.00",
        "mora_generado": "0.00",
        "paso_por_task": false
    }
},
{
    "model": "financings.paymentplan",
    "pk": 23,
    "fields": {
        "mes": 2,
        "start_date": "2024-11-02T06:00:00Z",
        "due_date": "2024-12-02T06:00:00Z",
        "outstanding_balance": "1096.00",
        "mora": "21.92",
        "interest": "219.20",
        "principal": "0.00",
        "principal_pagado": "0.00",
        "installment": "1205.60",
        "status": false,
        "credit_id": 5,
        "saldo_pendiente": "1096.00",
        "interes_pagado": "0.00",
        "mora_pagado": "0.00",
        "fecha_limite": "2024-12-18T06:00:00Z",
        "cambios": false,
        "numero_referencia": "NAN",
        "cuota_vencida": true,
        "interes_generado": "109.60",
        "capital_generado": "1096.00",
        "interes_acumulado_generado": "109.60",
        "mora_acumulado_generado": "10.96",
        "mora_generado": "0.00",
        "paso_por_task": false
    }
},
{
    "model": "financings.paymentplan",
    "pk": 24,
    "fields": {
        "mes": 3,
        "start_date": "2024-12-02T06:00:00Z",
        "due_date": "2025-01-02T06:00:00Z",
        "outstanding_balance": "1096.00",
        "mora": "21.92",
        "interest": "328.80",
        "principal": "0.00",
        "principal_pagado": "0.00",
        "installment": "1205.60",
        "status": false,
        "credit_id": 5,
        "saldo_pendiente": "1096.00",
        "interes_pagado": "0.00",
        "mora_pagado": "0.00",
        "fecha_limite": "2025-01-18T06:00:00Z",
        "cambios": false,
        "numero_referencia": "NAN",
        "cuota_vencida": false,
        "interes_generado": "109.60",
        "capital_generado": "1096.00",
        "interes_acumulado_generado": "219.20",
        "mora_acumulado_generado": "21.92",
        "mora_generado": "0.00",
        "paso_por_task": false
    }
},
{
    "model": "financings.paymentplan",
    "pk": 25,
    "fields": {
        "mes": 1,
        "start_date": "2024-10-02T06:00:00Z",
        "due_date": "2024-11-02T06:00:00Z",
        "outstanding_balance": "1096.00",
        "mora": "10.96",
        "interest": "109.60",
        "principal": "0.00",
        "principal_pagado": "0.00",
        "installment": "1205.60",
        "status": false,
        "credit_id": 6,
        "saldo_pendiente": "1096.00",
        "interes_pagado": "0.00",
        "mora_pagado": "0.00",
        "fecha_limite": "2024-11-18T06:00:00Z",
        "cambios": false,
        "numero_referencia": "NAN",
        "cuota_vencida": true,
        "interes_generado": "109.60",
        "capital_generado": "1096.00",
        "interes_acumulado_generado": "0.00",
        "mora_acumulado_generado": "0.00",
        "mora_generado": "0.00",
        "paso_por_task": false
    }
},
{
    "model": "financings.paymentplan",
    "pk": 26,
    "fields": {
        "mes": 2,
        "start_date": "2024-11-02T06:00:00Z",
        "due_date": "2024-12-02T06:00:00Z",
        "outstanding_balance": "1096.00",
        "mora": "21.92",
        "interest": "219.20",
        "principal": "0.00",
        "principal_pagado": "0.00",
        "installment": "1205.60",
        "status": false,
        "credit_id": 6,
        "saldo_pendiente": "1096.00",
        "interes_pagado": "0.00",
        "mora_pagado": "0.00",
        "fecha_limite": "2024-12-18T06:00:00Z",
        "cambios": false,
        "numero_referencia": "NAN",
        "cuota_vencida": true,
        "interes_generado": "109.60",
        "capital_generado": "1096.00",
        "interes_acumulado_generado": "109.60",
        "mora_acumulado_generado": "10.96",
        "mora_generado": "0.00",
        "paso_por_task": false
    }
},
{
    "model": "financings.paymentplan",
    "pk": 27,
    "fields": {
        "mes": 3,
        "start_date": "2024-12-02T06:00:00Z",
        "due_date": "2025-01-02T06:00:00Z",
        "outstanding_balance": "1096.00",
        "mora": "21.92",
        "interest": "328.80",
        "principal": "0.00",
        "principal_pagado": "0.00",
        "installment": "1205.60",
        "status": false,
        "credit_id": 6,
        "saldo_pendiente": "1096.00",
        "interes_pagado": "0.00",
        "mora_pagado": "0.00",
        "fecha_limite": "2025-01-18T06:00:00Z",
        "cambios": false,
        "numero_referencia": "NAN",
        "cuota_vencida": false,
        "interes_generado": "109.60",
        "capital_generado": "1096.00",
        "interes_acumulado_generado": "219.20",
        "mora_acumulado_generado": "21.92",
        "mora_generado": "0.00",
        "paso_por_task": false
    }
},
{
    "model": "financings.paymentplan",
    "pk": 28,
    "fields": {
        "mes": 1,
        "start_date": "2024-10-02T06:00:00Z",
        "due_date": "2024-11-02T06:00:00Z",
        "outstanding_balance": "1096.00",
        "mora": "10.96",
        "interest": "109.60",
        "principal": "0.00",
        "principal_pagado": "0.00",
        "installment": "631.50",
        "status": false,
        "credit_id": 7,
        "saldo_pendiente": "1096.00",
        "interes_pagado": "0.00",
        "mora_pagado": "0.00",
        "fecha_limite": "2024-11-18T06:00:00Z",
        "cambios": false,
        "numero_referencia": "NAN",
        "cuota_vencida": true,
        "interes_generado": "109.60",
        "capital_generado": "521.90",
        "interes_acumulado_generado": "0.00",
        "mora_acumulado_generado": "0.00",
        "mora_generado": "0.00",
        "paso_por_task": false
    }
},
{
    "model": "financings.paymentplan",
    "pk": 29,
    "fields": {
        "mes": 2,
        "start_date": "2024-11-02T06:00:00Z",
        "due_date": "2024-12-02T06:00:00Z",
        "outstanding_balance": "1096.00",
        "mora": "21.92",
        "interest": "219.20",
        "principal": "0.00",
        "principal_pagado": "0.00",
        "installment": "631.50",
        "status": false,
        "credit_id": 7,
        "saldo_pendiente": "1096.00",
        "interes_pagado": "0.00",
        "mora_pagado": "0.00",
        "fecha_limite": "2024-12-18T06:00:00Z",
        "cambios": false,
        "numero_referencia": "NAN",
        "cuota_vencida": true,
        "interes_generado": "109.60",
        "capital_generado": "521.90",
        "interes_acumulado_generado": "109.60",
        "mora_acumulado_generado": "10.96",
        "mora_generado": "0.00",
        "paso_por_task": false
    }
},
{
    "model": "financings.paymentplan",
    "pk": 30,
    "fields": {
        "mes": 3,
        "start_date": "2024-12-02T06:00:00Z",
        "due_date": "2025-01-02T06:00:00Z",
        "outstanding_balance": "1096.00",
        "mora": "21.92",
        "interest": "328.80",
        "principal": "0.00",
        "principal_pagado": "0.00",
        "installment": "631.50",
        "status": false,
        "credit_id": 7,
        "saldo_pendiente": "1096.00",
        "interes_pagado": "0.00",
        "mora_pagado": "0.00",
        "fecha_limite": "2025-01-18T06:00:00Z",
        "cambios": false,
        "numero_referencia": "NAN",
        "cuota_vencida": false,
        "interes_generado": "109.60",
        "capital_generado": "521.90",
        "interes_acumulado_generado": "219.20",
        "mora_acumulado_generado": "21.92",
        "mora_generado": "0.00",
        "paso_por_task": false
    }
},
{
    "model": "financings.paymentplan",
    "pk": 31,
    "fields": {
        "mes": 1,
        "start_date": "2024-10-02T06:00:00Z",
        "due_date": "2024-11-02T06:00:00Z",
        "outstanding_balance": "3200.00",
        "mora": "32.00",
        "interest": "320.00",
        "principal": "0.00",
        "principal_pagado": "0.00",
        "installment": "1286.77",
        "status": false,
        "credit_id": 8,
        "saldo_pendiente": "3200.00",
        "interes_pagado": "0.00",
        "mora_pagado": "0.00",
        "fecha_limite": "2024-11-18T06:00:00Z",
        "cambios": false,
        "numero_referencia": "NAN",
        "cuota_vencida": true,
        "interes_generado": "320.00",
        "capital_generado": "966.77",
        "interes_acumulado_generado": "0.00",
        "mora_acumulado_generado": "0.00",
        "mora_generado": "0.00",
        "paso_por_task": false
    }
},
{
    "model": "financings.paymentplan",
    "pk": 32,
    "fields": {
        "mes": 2,
        "start_date": "2024-11-02T06:00:00Z",
        "due_date": "2024-12-02T06:00:00Z",
        "outstanding_balance": "3200.00",
        "mora": "64.00",
        "interest": "640.00",
        "principal": "0.00",
        "principal_pagado": "0.00",
        "installment": "1286.77",
        "status": false,
        "credit_id": 8,
        "saldo_pendiente": "3200.00",
        "interes_pagado": "0.00",
        "mora_pagado": "0.00",
        "fecha_limite": "2024-12-18T06:00:00Z",
        "cambios": false,
        "numero_referencia": "NAN",
        "cuota_vencida": true,
        "interes_generado": "320.00",
        "capital_generado": "966.77",
        "interes_acumulado_generado": "320.00",
        "mora_acumulado_generado": "32.00",
        "mora_generado": "0.00",
        "paso_por_task": false
    }
},
{
    "model": "financings.paymentplan",
    "pk": 33,
    "fields": {
        "mes": 3,
        "start_date": "2024-12-02T06:00:00Z",
        "due_date": "2025-01-02T06:00:00Z",
        "outstanding_balance": "3200.00",
        "mora": "64.00",
        "interest": "960.00",
        "principal": "0.00",
        "principal_pagado": "0.00",
        "installment": "1286.77",
        "status": false,
        "credit_id": 8,
        "saldo_pendiente": "3200.00",
        "interes_pagado": "0.00",
        "mora_pagado": "0.00",
        "fecha_limite": "2025-01-18T06:00:00Z",
        "cambios": false,
        "numero_referencia": "NAN",
        "cuota_vencida": false,
        "interes_generado": "320.00",
        "capital_generado": "966.77",
        "interes_acumulado_generado": "640.00",
        "mora_acumulado_generado": "64.00",
        "mora_generado": "0.00",
        "paso_por_task": false
    }
},
{
    "model": "financings.paymentplan",
    "pk": 34,
    "fields": {
        "mes": 1,
        "start_date": "2024-10-02T06:00:00Z",
        "due_date": "2024-11-02T06:00:00Z",
        "outstanding_balance": "2000.00",
        "mora": "20.00",
        "interest": "200.00",
        "principal": "0.00",
        "principal_pagado": "0.00",
        "installment": "804.23",
        "status": false,
        "credit_id": 9,
        "saldo_pendiente": "2000.00",
        "interes_pagado": "0.00",
        "mora_pagado": "0.00",
        "fecha_limite": "2024-11-18T06:00:00Z",
        "cambios": false,
        "numero_referencia": "NAN",
        "cuota_vencida": true,
        "interes_generado": "200.00",
        "capital_generado": "604.23",
        "interes_acumulado_generado": "0.00",
        "mora_acumulado_generado": "0.00",
        "mora_generado": "0.00",
        "paso_por_task": false
    }
},
{
    "model": "financings.paymentplan",
    "pk": 35,
    "fields": {
        "mes": 2,
        "start_date": "2024-11-02T06:00:00Z",
        "due_date": "2024-12-02T06:00:00Z",
        "outstanding_balance": "2000.00",
        "mora": "40.00",
        "interest": "400.00",
        "principal": "0.00",
        "principal_pagado": "0.00",
        "installment": "804.23",
        "status": false,
        "credit_id": 9,
        "saldo_pendiente": "2000.00",
        "interes_pagado": "0.00",
        "mora_pagado": "0.00",
        "fecha_limite": "2024-12-18T06:00:00Z",
        "cambios": false,
        "numero_referencia": "NAN",
        "cuota_vencida": true,
        "interes_generado": "200.00",
        "capital_generado": "604.23",
        "interes_acumulado_generado": "200.00",
        "mora_acumulado_generado": "20.00",
        "mora_generado": "0.00",
        "paso_por_task": false
    }
},
{
    "model": "financings.paymentplan",
    "pk": 36,
    "fields": {
        "mes": 3,
        "start_date": "2024-12-02T06:00:00Z",
        "due_date": "2025-01-02T06:00:00Z",
        "outstanding_balance": "2000.00",
        "mora": "40.00",
        "interest": "600.00",
        "principal": "0.00",
        "principal_pagado": "0.00",
        "installment": "804.23",
        "status": false,
        "credit_id": 9,
        "saldo_pendiente": "2000.00",
        "interes_pagado": "0.00",
        "mora_pagado": "0.00",
        "fecha_limite": "2025-01-18T06:00:00Z",
        "cambios": false,
        "numero_referencia": "NAN",
        "cuota_vencida": false,
        "interes_generado": "200.00",
        "capital_generado": "604.23",
        "interes_acumulado_generado": "400.00",
        "mora_acumulado_generado": "40.00",
        "mora_generado": "0.00",
        "paso_por_task": false
    }
},
{
    "model": "financings.paymentplan",
    "pk": 37,
    "fields": {
        "mes": 1,
        "start_date": "2024-10-02T06:00:00Z",
        "due_date": "2024-11-02T06:00:00Z",
        "outstanding_balance": "3000.00",
        "mora": "30.00",
        "interest": "300.00",
        "principal": "0.00",
        "principal_pagado": "0.00",
        "installment": "688.82",
        "status": false,
        "credit_id": 10,
        "saldo_pendiente": "3000.00",
        "interes_pagado": "0.00",
        "mora_pagado": "0.00",
        "fecha_limite": "2024-11-18T06:00:00Z",
        "cambios": false,
        "numero_referencia": "NAN",
        "cuota_vencida": true,
        "interes_generado": "300.00",
        "capital_generado": "388.82",
        "interes_acumulado_generado": "0.00",
        "mora_acumulado_generado": "0.00",
        "mora_generado": "0.00",
        "paso_por_task": false
    }
},
{
    "model": "financings.paymentplan",
    "pk": 38,
    "fields": {
        "mes": 2,
        "start_date": "2024-11-02T06:00:00Z",
        "due_date": "2024-12-02T06:00:00Z",
        "outstanding_balance": "3000.00",
        "mora": "60.00",
        "interest": "600.00",
        "principal": "0.00",
        "principal_pagado": "0.00",
        "installment": "688.82",
        "status": false,
        "credit_id": 10,
        "saldo_pendiente": "3000.00",
        "interes_pagado": "0.00",
        "mora_pagado": "0.00",
        "fecha_limite": "2024-12-18T06:00:00Z",
        "cambios": false,
        "numero_referencia": "NAN",
        "cuota_vencida": true,
        "interes_generado": "300.00",
        "capital_generado": "388.82",
        "interes_acumulado_generado": "300.00",
        "mora_acumulado_generado": "30.00",
        "mora_generado": "0.00",
        "paso_por_task": false
    }
},
{
    "model": "financings.paymentplan",
    "pk": 39,
    "fields": {
        "mes": 3,
        "start_date": "2024-12-02T06:00:00Z",
        "due_date": "2025-01-02T06:00:00Z",
        "outstanding_balance": "3000.00",
        "mora": "60.00",
        "interest": "900.00",
        "principal": "0.00",
        "principal_pagado": "0.00",
        "installment": "688.82",
        "status": false,
        "credit_id": 10,
        "saldo_pendiente": "3000.00",
        "interes_pagado": "0.00",
        "mora_pagado": "0.00",
        "fecha_limite": "2025-01-18T06:00:00Z",
        "cambios": false,
        "numero_referencia": "NAN",
        "cuota_vencida": false,
        "interes_generado": "300.00",
        "capital_generado": "388.82",
        "interes_acumulado_generado": "600.00",
        "mora_acumulado_generado": "60.00",
        "mora_generado": "0.00",
        "paso_por_task": false
    }
},
{
    "model": "financings.paymentplan",
    "pk": 40,
    "fields": {
        "mes": 1,
        "start_date": "2024-10-02T06:00:00Z",
        "due_date": "2024-11-02T06:00:00Z",
        "outstanding_balance": "7000.00",
        "mora": "70.00",
        "interest": "700.00",
        "principal": "0.00",
        "principal_pagado": "0.00",
        "installment": "1607.25",
        "status": false,
        "credit_id": 11,
        "saldo_pendiente": "7000.00",
        "interes_pagado": "0.00",
        "mora_pagado": "0.00",
        "fecha_limite": "2024-11-18T06:00:00Z",
        "cambios": false,
        "numero_referencia": "NAN",
        "cuota_vencida": true,
        "interes_generado": "700.00",
        "capital_generado": "907.25",
        "interes_acumulado_generado": "0.00",
        "mora_acumulado_generado": "0.00",
        "mora_generado": "0.00",
        "paso_por_task": false
    }
},
{
    "model": "financings.paymentplan",
    "pk": 41,
    "fields": {
        "mes": 2,
        "start_date": "2024-11-02T06:00:00Z",
        "due_date": "2024-12-02T06:00:00Z",
        "outstanding_balance": "7000.00",
        "mora": "140.00",
        "interest": "1400.00",
        "principal": "0.00",
        "principal_pagado": "0.00",
        "installment": "1607.25",
        "status": false,
        "credit_id": 11,
        "saldo_pendiente": "7000.00",
        "interes_pagado": "0.00",
        "mora_pagado": "0.00",
        "fecha_limite": "2024-12-18T06:00:00Z",
        "cambios": false,
        "numero_referencia": "NAN",
        "cuota_vencida": true,
        "interes_generado": "700.00",
        "capital_generado": "907.25",
        "interes_acumulado_generado": "700.00",
        "mora_acumulado_generado": "70.00",
        "mora_generado": "0.00",
        "paso_por_task": false
    }
},
{
    "model": "financings.paymentplan",
    "pk": 42,
    "fields": {
        "mes": 3,
        "start_date": "2024-12-02T06:00:00Z",
        "due_date": "2025-01-02T06:00:00Z",
        "outstanding_balance": "7000.00",
        "mora": "140.00",
        "interest": "2100.00",
        "principal": "0.00",
        "principal_pagado": "0.00",
        "installment": "1607.25",
        "status": false,
        "credit_id": 11,
        "saldo_pendiente": "7000.00",
        "interes_pagado": "0.00",
        "mora_pagado": "0.00",
        "fecha_limite": "2025-01-18T06:00:00Z",
        "cambios": false,
        "numero_referencia": "NAN",
        "cuota_vencida": false,
        "interes_generado": "700.00",
        "capital_generado": "907.25",
        "interes_acumulado_generado": "1400.00",
        "mora_acumulado_generado": "140.00",
        "mora_generado": "0.00",
        "paso_por_task": false
    }
},
{
    "model": "financings.paymentplan",
    "pk": 43,
    "fields": {
        "mes": 1,
        "start_date": "2024-10-03T06:00:00Z",
        "due_date": "2024-11-03T06:00:00Z",
        "outstanding_balance": "7000.00",
        "mora": "70.00",
        "interest": "700.00",
        "principal": "0.00",
        "principal_pagado": "0.00",
        "installment": "2814.80",
        "status": false,
        "credit_id": 12,
        "saldo_pendiente": "7000.00",
        "interes_pagado": "0.00",
        "mora_pagado": "0.00",
        "fecha_limite": "2024-11-19T06:00:00Z",
        "cambios": false,
        "numero_referencia": "NAN",
        "cuota_vencida": true,
        "interes_generado": "700.00",
        "capital_generado": "2114.80",
        "interes_acumulado_generado": "0.00",
        "mora_acumulado_generado": "0.00",
        "mora_generado": "0.00",
        "paso_por_task": false
    }
},
{
    "model": "financings.paymentplan",
    "pk": 44,
    "fields": {
        "mes": 2,
        "start_date": "2024-11-03T06:00:00Z",
        "due_date": "2024-12-03T06:00:00Z",
        "outstanding_balance": "7000.00",
        "mora": "140.00",
        "interest": "1400.00",
        "principal": "0.00",
        "principal_pagado": "0.00",
        "installment": "2814.80",
        "status": false,
        "credit_id": 12,
        "saldo_pendiente": "7000.00",
        "interes_pagado": "0.00",
        "mora_pagado": "0.00",
        "fecha_limite": "2024-12-19T06:00:00Z",
        "cambios": false,
        "numero_referencia": "NAN",
        "cuota_vencida": true,
        "interes_generado": "700.00",
        "capital_generado": "2114.80",
        "interes_acumulado_generado": "700.00",
        "mora_acumulado_generado": "70.00",
        "mora_generado": "0.00",
        "paso_por_task": false
    }
},
{
    "model": "financings.paymentplan",
    "pk": 45,
    "fields": {
        "mes": 3,
        "start_date": "2024-12-03T06:00:00Z",
        "due_date": "2025-01-03T06:00:00Z",
        "outstanding_balance": "7000.00",
        "mora": "140.00",
        "interest": "2100.00",
        "principal": "0.00",
        "principal_pagado": "0.00",
        "installment": "2814.80",
        "status": false,
        "credit_id": 12,
        "saldo_pendiente": "7000.00",
        "interes_pagado": "0.00",
        "mora_pagado": "0.00",
        "fecha_limite": "2025-01-19T06:00:00Z",
        "cambios": false,
        "numero_referencia": "NAN",
        "cuota_vencida": false,
        "interes_generado": "700.00",
        "capital_generado": "2114.80",
        "interes_acumulado_generado": "1400.00",
        "mora_acumulado_generado": "140.00",
        "mora_generado": "0.00",
        "paso_por_task": false
    }
}
]
